tkitElasticsearch/__init__.py
tkitElasticsearch/keywords.py
tkitElasticsearch/search.py
tkitElasticsearch/tkitElasticsearch.py
tkitElasticsearch-0.0.0.116393000.dist-info/METADATA
tkitElasticsearch-0.0.0.116393000.dist-info/WHEEL
tkitElasticsearch-0.0.0.116393000.dist-info/top_level.txt
tkitElasticsearch-0.0.0.116393000.dist-info/RECORD
