Metadata-Version: 2.1
Name: tkitElasticsearch
Version: 0.0.0.116393000
Summary: Terry tkitElasticsearch ,
Home-page: https://terrychan.org
Author: Terry Chan
Author-email: napoler2008@gmail.com
License: UNKNOWN
Platform: UNKNOWN
Requires-Dist: elasticsearch (==7.16.0)
Requires-Dist: elasticsearch-dsl (==7.4.0)
